{
  "id": "vasp-s7",
  "content": "Section 7 — Guiding principles of the relevant regulatory authorities\n\nThe relevant regulatory authorities shall, in exercising their powers and in performing their functions under this Act, be guided by the following principles—\n(a) to ensure financial stability in Kenya;\n(b) to ensure market integrity in Kenya;\n(c) to foster innovation and maintain fairness, transparency and efficiency in the virtual assets sector in Kenya; and\n(d) to prevent, detect and restrain conduct that causes or may cause damage to the financial reputation of Kenya.",
  "word_count": 84,
  "has_table": false,
  "has_list": true
}